MANIFEST.in
README.rst
setup.py
examples/logging.conf
pubsub_logging/__init__.py
pubsub_logging/async_handler.py
pubsub_logging/errors.py
pubsub_logging/pubsub_handler.py
pubsub_logging/utils.py
pubsub_logging.egg-info/PKG-INFO
pubsub_logging.egg-info/SOURCES.txt
pubsub_logging.egg-info/dependency_links.txt
pubsub_logging.egg-info/requires.txt
pubsub_logging.egg-info/top_level.txt