Metadata-Version: 1.1
Name: pubsub-logging
Version: 0.2.0
Summary: Logging handlers for publishing the logs to Cloud Pub/Sub
Home-page: https://github.com/GoogleCloudPlatform/cloud-pubsub-logging-python
Author: Takashi Matsuo
Author-email: tmatsuo@google.com
License: Apache 2.0
Platform: UNKNOWN
Classifier: Programming Language :: Python :: 2
Classifier: Programming Language :: Python :: 3
Classifier: Intended Audience :: Developers
Classifier: License :: OSI Approved :: Apache Software License
Classifier: Topic :: Software Development :: Libraries
Classifier: Topic :: Utilities
